zabbixci/__init__.py
zabbixci/_version.py
zabbixci/cli.py
zabbixci/exceptions.py
zabbixci/logging.py
zabbixci/settings.py
zabbixci/zabbixci.py
zabbixci/assets/__init__.py
zabbixci/assets/asset.py
zabbixci/assets/icon_map.py
zabbixci/assets/image.py
zabbixci/assets/template.py
zabbixci/cache/__init__.py
zabbixci/cache/cache.py
zabbixci/cache/cleanup.py
zabbixci/cache/filesystem.py
zabbixci/git/__init__.py
zabbixci/git/credentials.py
zabbixci/git/git.py
zabbixci/handlers/__init__.py
zabbixci/handlers/synchronization/__init__.py
zabbixci/handlers/synchronization/icon_map_synchronization.py
zabbixci/handlers/synchronization/image_synchronization.py
zabbixci/handlers/synchronization/imagemagick_synchronization.py
zabbixci/handlers/synchronization/template_synchronization.py
zabbixci/handlers/validation/__init__.py
zabbixci/handlers/validation/icon_map_validation.py
zabbixci/handlers/validation/image_validation.py
zabbixci/handlers/validation/template_validation.py
zabbixci/handlers/validation/validation_handler.py
zabbixci/zabbix/__init__.py
zabbixci/zabbix/zabbix.py
zabbixci-0.3.11.dist-info/licenses/LICENSE.txt
zabbixci-0.3.11.dist-info/METADATA
zabbixci-0.3.11.dist-info/WHEEL
zabbixci-0.3.11.dist-info/entry_points.txt
zabbixci-0.3.11.dist-info/top_level.txt
zabbixci-0.3.11.dist-info/RECORD
