Metadata-Version: 2.4
Name: zabbixci
Version: 0.3.11
Summary: Source control for Zabbix templates in Git
Author-email: Retigra <info@retigra.nl>
Maintainer-email: Wouter de Bruijn <wouter.debruijn@retigra.nl>, Raymond Kuiper <raymond.kuiper@retigra.nl>
Project-URL: Homepage, https://github.com/retigra/zabbixci
Project-URL: Repository, https://github.com/retigra/zabbixci
Project-URL: Issues, https://github.com/retigra/zabbixci/issues
Project-URL: Changelog, https://github.com/retigra/zabbixci/releases
Project-URL: Discussions, https://github.com/retigra/ZabbixCI/discussions
Keywords: zabbix,git,source control,templates
Classifier: Development Status :: 4 - Beta
Classifier: Intended Audience :: Developers
Classifier: Intended Audience :: System Administrators
Classifier: Programming Language :: Python :: 3
Classifier: Programming Language :: Python :: 3.6
Classifier: Programming Language :: Python :: 3.7
Classifier: Programming Language :: Python :: 3.8
Classifier: Programming Language :: Python :: 3.9
Classifier: Programming Language :: Python :: 3.10
Classifier: Operating System :: OS Independent
Classifier: Topic :: Software Development :: Version Control
Classifier: Topic :: System :: Monitoring
Classifier: Topic :: System :: Networking :: Monitoring
Classifier: Topic :: System :: Systems Administration
Classifier: Topic :: Utilities
Classifier: Environment :: Console
License-File: LICENSE.txt
Requires-Dist: aiohttp>=3.12.14
Requires-Dist: pygit2>=1.18.0
Requires-Dist: regex>=2024.11.6
Requires-Dist: ruamel.yaml>=0.18.13
Requires-Dist: zabbix_utils>=2.0.3
Requires-Dist: Wand>=0.6.13
Provides-Extra: dev
Requires-Dist: black>=24.10.0; extra == "dev"
Requires-Dist: isort>=5.13.2; extra == "dev"
Requires-Dist: flake8>=7.1.1; extra == "dev"
Dynamic: license-file
